<annotation>
	<folder>labelled-non-fire</folder>
	<filename>172.jpg</filename>
	<path>C:\Users\jainv\OneDrive\Desktop\Fire Detection\DL-Workshop\labelled-non-fire\172.jpg</path>
	<source>
		<database>Unknown</database>
	</source>
	<size>
		<width>697</width>
		<height>437</height>
		<depth>3</depth>
	</size>
	<segmented>0</segmented>
	<object>
		<name>brightspot</name>
		<pose>Unspecified</pose>
		<truncated>0</truncated>
		<difficult>0</difficult>
		<bndbox>
			<xmin>92</xmin>
			<ymin>36</ymin>
			<xmax>105</xmax>
			<ymax>45</ymax>
		</bndbox>
	</object>
	<object>
		<name>brightspot</name>
		<pose>Unspecified</pose>
		<truncated>0</truncated>
		<difficult>0</difficult>
		<bndbox>
			<xmin>362</xmin>
			<ymin>23</ymin>
			<xmax>369</xmax>
			<ymax>34</ymax>
		</bndbox>
	</object>
</annotation>
