<annotation>
	<folder>notfire</folder>
	<filename>378.jpg</filename>
	<path>C:\Users\jainv\OneDrive\Desktop\Fire Detection\DL-Workshop\notfire\378.jpg</path>
	<source>
		<database>Unknown</database>
	</source>
	<size>
		<width>400</width>
		<height>267</height>
		<depth>3</depth>
	</size>
	<segmented>0</segmented>
	<object>
		<name>brightspot</name>
		<pose>Unspecified</pose>
		<truncated>0</truncated>
		<difficult>0</difficult>
		<bndbox>
			<xmin>83</xmin>
			<ymin>69</ymin>
			<xmax>125</xmax>
			<ymax>88</ymax>
		</bndbox>
	</object>
	<object>
		<name>brightspot</name>
		<pose>Unspecified</pose>
		<truncated>0</truncated>
		<difficult>0</difficult>
		<bndbox>
			<xmin>184</xmin>
			<ymin>59</ymin>
			<xmax>195</xmax>
			<ymax>79</ymax>
		</bndbox>
	</object>
</annotation>
