<annotation>
	<folder>notfire</folder>
	<filename>488.jpg</filename>
	<path>C:\Users\jainv\OneDrive\Desktop\notfire\488.jpg</path>
	<source>
		<database>Unknown</database>
	</source>
	<size>
		<width>900</width>
		<height>600</height>
		<depth>3</depth>
	</size>
	<segmented>0</segmented>
	<object>
		<name>brightspot</name>
		<pose>Unspecified</pose>
		<truncated>0</truncated>
		<difficult>0</difficult>
		<bndbox>
			<xmin>420</xmin>
			<ymin>473</ymin>
			<xmax>476</xmax>
			<ymax>517</ymax>
		</bndbox>
	</object>
</annotation>
